docs/source/conf.py
numba_scfg/__init__.py
numba_scfg/core/transformations.py
numba_scfg/core/utils.py
numba_scfg/core/datastructures/ast_transforms.py
numba_scfg/core/datastructures/basic_block.py
numba_scfg/core/datastructures/block_names.py
numba_scfg/core/datastructures/byte_flow.py
numba_scfg/core/datastructures/flow_info.py
numba_scfg/core/datastructures/scfg.py
numba_scfg/networkx_vendored/scc.py
numba_scfg/rendering/rendering.py
numba_scfg/tests/mock_asm.py
numba_scfg/tests/simulator.py
numba_scfg/tests/test_ast_transforms.py
numba_scfg/tests/test_byteflow.py
numba_scfg/tests/test_figures.py
numba_scfg/tests/test_mock_asm.py
numba_scfg/tests/test_rendering.py
numba_scfg/tests/test_scc.py
numba_scfg/tests/test_scfg.py
numba_scfg/tests/test_simulate.py
numba_scfg/tests/test_transforms.py
numba_scfg/tests/test_utils.py
numba_scfg-0.0.8.dist-info/LICENSE
numba_scfg-0.0.8.dist-info/METADATA
numba_scfg-0.0.8.dist-info/WHEEL
numba_scfg-0.0.8.dist-info/top_level.txt
numba_scfg-0.0.8.dist-info/RECORD
